{
  "json": {
    "data": {
      "age": 30,
      "city": "New York",
      "isStudent": false,
      "name": "John"
    },
    "type": "json"
  },
  "markdown": "<p>This is <em>markdown</em> <ins>content</ins>.</p>",
  "sub1": {
    "hey": {
      "location": 1
    }
  },
  "sub2": {
    "hey": {
      "location": 2
    }
  },
  "yaml": {
    "data": [
      {
        "age": 30,
        "name": "John Doe",
        "student": false
      },
      {
        "age": 25,
        "date": "2021-12-31",
        "name": "Jane Doe",
        "norway": false
      }
    ],
    "type": "YAML"
  },
  "yaml-long-extension": {
    "type": "YAML"
  }
}
